random_standup/__init__.py
random_standup/standup.py
random_standup-1.0.0.dist-info/entry_points.txt
random_standup-1.0.0.dist-info/LICENSE
random_standup-1.0.0.dist-info/WHEEL
random_standup-1.0.0.dist-info/METADATA
random_standup-1.0.0.dist-info/RECORD
