Metadata-Version: 2.1
Name: random-standup
Version: 1.0.0
Summary: Standup Randomizer
Home-page: https://github.com/jidicula/random-standup-py
License: BSD 3-Clause License
Keywords: agile,standup
Author: jidicula
Author-email: johanan@forcepush.tech
Requires-Python: >=3.7,<4.0
Classifier: Development Status :: 5 - Production/Stable
Classifier: License :: OSI Approved :: BSD License
Classifier: License :: Other/Proprietary License
Classifier: Operating System :: MacOS
Classifier: Operating System :: Microsoft :: Windows
Classifier: Operating System :: POSIX :: Linux
Classifier: Programming Language :: Python :: 3
Classifier: Programming Language :: Python :: 3.7
Classifier: Programming Language :: Python :: 3.8
Classifier: Programming Language :: Python :: 3.9
Classifier: Topic :: Office/Business
Requires-Dist: click (>=7.1.2,<8.0.0)
Requires-Dist: tomlkit (>=0.7.0,<0.8.0)
Project-URL: Documentation, https://github.com/jidicula/random-standup-py
Project-URL: Repository, https://github.com/jidicula/random-standup-py
